gplas/.gitkeep
gplas/__init__.py
gplas/gplas.py
gplas/logo.txt
gplas/version.py
gplas/scripts/__init__.py
gplas/scripts/check_prediction_format.py
gplas/scripts/coocurrence.py
gplas/scripts/coocurrence_repeats.py
gplas/scripts/coverage.py
gplas/scripts/node_extraction.py
gplas/scripts/paths.py
gplas/scripts/paths_repeats.py
gplas/scripts/run_plasmidcc.py
gplas/scripts/utils.py
gplas-1.0.1.dist-info/licenses/LICENSE
gplas-1.0.1.dist-info/METADATA
gplas-1.0.1.dist-info/WHEEL
gplas-1.0.1.dist-info/entry_points.txt
gplas-1.0.1.dist-info/top_level.txt
gplas-1.0.1.dist-info/RECORD
