Metadata-Version: 2.4
Name: gplas
Version: 1.0.1
Summary: Binning plasmid-predicted contigs using short-read graphs
License-File: LICENSE
Requires-Dist: biopython>=1.83
Requires-Dist: cairocffi>=1.6.1
Requires-Dist: numpy>=1.26.4
Requires-Dist: pandas>=2.2.0
Requires-Dist: python-igraph>=0.11.3
Requires-Dist: scipy>=1.12.0
Requires-Dist: plasmidCC>=1.0.0
Dynamic: description
Dynamic: description-content-type
Dynamic: license-file
Dynamic: requires-dist
Dynamic: summary
